README.txt
setup.py
collective/__init__.py
collective.funkbot.egg-info/PKG-INFO
collective.funkbot.egg-info/SOURCES.txt
collective.funkbot.egg-info/dependency_links.txt
collective.funkbot.egg-info/entry_points.txt
collective.funkbot.egg-info/namespace_packages.txt
collective.funkbot.egg-info/not-zip-safe
collective.funkbot.egg-info/paster_plugins.txt
collective.funkbot.egg-info/requires.txt
collective.funkbot.egg-info/top_level.txt
collective/funkbot/__init__.py
collective/funkbot/funkbot.py
collective/funkbot/tests.py
collective/funkbot/templates/funkbot/bootstrap.py
collective/funkbot/templates/funkbot/buildout.cfg_tmpl
collective/funkbot/templates/funkbot/mail.ini_tmpl
collective/funkbot/templates/funkbot/make_reports.sh_tmpl
collective/funkbot/templates/funkbot/sendmail.py_tmpl
collective/funkbot/templates/funkbot/config/buildbot.cfg_tmpl
collective/funkbot/templates/funkbot/config/candidate.cfg
collective/funkbot/templates/funkbot/config/coreloadtests.cfg
collective/funkbot/templates/funkbot/config/funkload.cfg
collective/funkbot/templates/funkbot/config/plone.cfg
collective/funkbot/templates/funkbot/config/zeo.cfg
collective/funkbot/templates/funkbot/etc/monitor.conf
collective/funkbot/templates/funkbot/etc/supervisord.conf
collective/funkbot/templates/funkbot/public_html/buildbot.css
docs/HISTORY.txt
docs/INSTALL.txt
docs/LICENSE.GPL
docs/LICENSE.txt