Metadata-Version: 1.0
Name: collective.funkbot
Version: 1.0
Summary: Using buildbot and funkload, allow you to have a feedback of your modifications of a python project with funkload differencial reports and buildbot waterfall
Home-page: https://svn.plone.org/svn/collective/collective.funkbot
Author: JeanMichel FRANCOIS
Author-email: jeanmichel.francois@makina-corpus.com
License: GPL
Platform: UNKNOWN
Classifier: Framework :: Plone
Classifier: Programming Language :: Python
